brocc/__about__.py
brocc/__init__.py
brocc/app.py
brocc/app.tcss
brocc/entry_points.py
brocc/lifecycle.py
brocc/browser/chrome_cdp.py
brocc/browser/chrome_manager.py
brocc/browser/chrome_process.py
brocc/browser/chrome_watcher.py
brocc/browser/determine_item_action.py
brocc/browser/diff_tab_state.py
brocc/browser/extract_metadata.py
brocc/browser/next_monitor_status.py
brocc/browser/tab_interaction_handler.py
brocc/browser/tab_monitor.py
brocc/browser/types.py
brocc/cli/cli_debug.py
brocc/cli/cli_main.py
brocc/db/const.py
brocc/db/core_model.py
brocc/db/lance_connection.py
brocc/db/lance_schema.py
brocc/db/normalize_datetime.py
brocc/db/search.py
brocc/db/sqlite_manager.py
brocc/db/sqlite_models.py
brocc/db/sqlite_session.py
brocc/internal/auth_data.py
brocc/internal/const.py
brocc/internal/env.py
brocc/internal/get_app_dir.py
brocc/internal/get_dir_size.py
brocc/internal/get_domain.py
brocc/internal/get_update.py
brocc/internal/get_version.py
brocc/internal/internal_api_client.py
brocc/internal/logger.py
brocc/internal/normalize_url.py
brocc/internal/site_api_client.py
brocc/internal/webview.py
brocc/parse/base_parser.py
brocc/parse/extract_feed_items.py
brocc/parse/html_parser.py
brocc/parse/id_from_url.py
brocc/parse/linkedin_post_parser.py
brocc/parse/parser_registry.py
brocc/parse/twitter_feed_parser.py
brocc/parse/twitter_thread_parser.py
brocc/parse/twitter_utils.py
brocc/parse/types.py
brocc/parse/utils.py
brocc/proc/__init__.py
brocc/proc/proc_webview.py
brocc/server/__init__.py
brocc/server/debouncer.py
brocc/server/fastapi.py
brocc/server/frontend_ws_manager.py
brocc/server/models.py
brocc/server/router_auth.py
brocc/server/router_chrome.py
brocc/server/router_data.py
brocc/server/router_websockets.py
brocc/server/router_webview.py
brocc/server/types.py
brocc/static/index.html
brocc/static/assets/index-BJwso8d-.js
brocc/static/assets/index-n3B6CAux.css
brocc/tasks/consumer.py
brocc/tasks/embed.py
brocc/tasks/exceptions.py
brocc/tasks/hash_content.py
brocc_cli-0.0.15.dist-info/METADATA
brocc_cli-0.0.15.dist-info/WHEEL
brocc_cli-0.0.15.dist-info/entry_points.txt
brocc_cli-0.0.15.dist-info/RECORD
