Metadata-Version: 2.4
Name: brocc-cli
Version: 0.0.15
Summary: Browser Companion
Project-URL: Documentation, https://brocc.ai
Author-email: Ben Guo <ben@substrate.run>
License-Expression: MIT
Keywords: AI,browser,search
Classifier: Development Status :: 4 - Beta
Classifier: Programming Language :: Python
Classifier: Programming Language :: Python :: 3.12
Classifier: Programming Language :: Python :: Implementation :: CPython
Classifier: Programming Language :: Python :: Implementation :: PyPy
Requires-Python: >=3.12
Requires-Dist: beautifulsoup4>=4.13.4
Requires-Dist: dateparser>=1.2.1
Requires-Dist: docling>=2.15.1
Requires-Dist: dotenv>=0.9.9
Requires-Dist: einops>=0.8.1
Requires-Dist: fastapi[all]>=0.115.12
Requires-Dist: hf-transfer>=0.1.9
Requires-Dist: hf-xet>=1.0.5
Requires-Dist: httpx>=0.28.1
Requires-Dist: huey>=2.5.3
Requires-Dist: lancedb>=0.21.2
Requires-Dist: lxml>=5.3.2
Requires-Dist: markdownify>=1.1.0
Requires-Dist: mlx-lm>=0.24.0
Requires-Dist: numpy>=2.2.5
Requires-Dist: openai>=1.76.0
Requires-Dist: packaging>=24.0
Requires-Dist: pandas>=2.2.3
Requires-Dist: platformdirs>=4.3.7
Requires-Dist: polars>=1.27.1
Requires-Dist: psutil>=7.0.0
Requires-Dist: pyarrow>=19.0.1
Requires-Dist: pylance>=0.26.0
Requires-Dist: pywebview>=5.4
Requires-Dist: rich>=13.9.4
Requires-Dist: sentence-transformers>=4.1.0
Requires-Dist: sqlalchemy>=2.0.40
Requires-Dist: textual>=3.1.0
Requires-Dist: uvicorn>=0.34.0
Requires-Dist: websocket-client>=1.8.0
Provides-Extra: dev
Requires-Dist: pyright>=1.1.400; extra == 'dev'
Requires-Dist: pytest-asyncio>=0.21.0; extra == 'dev'
Requires-Dist: pytest-mock; extra == 'dev'
Requires-Dist: pytest>=7.0; extra == 'dev'
Requires-Dist: ruff>=0.3.0; extra == 'dev'
Requires-Dist: term-image~=0.7.2; extra == 'dev'
